password_agent.py
syborg.py
syborg-1.0.0.data/data/share/syborg/syborg-backup@.service
syborg-1.0.0.data/data/share/syborg/syborg-backup@.timer
syborg-1.0.0.data/data/share/syborg/syborg-example.cfg
syborg-1.0.0.data/data/share/syborg/systemd-gtk-ask-password-agent.desktop
syborg-1.0.0.dist-info/LICENSE
syborg-1.0.0.dist-info/METADATA
syborg-1.0.0.dist-info/WHEEL
syborg-1.0.0.dist-info/entry_points.txt
syborg-1.0.0.dist-info/top_level.txt
syborg-1.0.0.dist-info/RECORD
