Metadata-Version: 2.1
Name: syborg
Version: 1.0.0
Summary: Nice borgbackup wrapper
Home-page: https://github.com/tarruda/syborg
Author: Thiago de Arruda Padilha
Author-email: tpadilha84@gmail.com
License: MIT
Download-URL: https://github.com/tarruda/syborg/archive/1.0.0.tar.gz
Platform: UNKNOWN
Requires-Dist: pexpect
Requires-Dist: pyxdg
Requires-Dist: ush
